Metadata-Version: 2.1
Name: etcd3-rs
Version: 0.13.0
Summary: Fork of https://github.com/kragniz/python-etcd3
Home-page: https://github.com/atzoum/python-etcd3
Author: Aris Tzoumas
Author-email: atzoumas@rudderstack.com
License: Apache Software License 2.0
Keywords: etcd3
Classifier: Development Status :: 2 - Pre-Alpha
Classifier: Intended Audience :: Developers
Classifier: License :: OSI Approved :: Apache Software License
Classifier: Natural Language :: English
Classifier: Programming Language :: Python :: 2
Classifier: Programming Language :: Python :: 2.7
Classifier: Programming Language :: Python :: 3
Classifier: Programming Language :: Python :: 3.4
Classifier: Programming Language :: Python :: 3.5
Classifier: Programming Language :: Python :: 3.6
License-File: LICENSE
License-File: AUTHORS.rst
Requires-Dist: grpcio (>=1.38.0)
Requires-Dist: protobuf (>=3.17.0)
Requires-Dist: six (>=1.16.0)
